{
  "recipes": {
    "capistrano": "",
    "capistrano": "Installs Capistrano gem"
  },
  "maintainer_email": "cookbooks@opscode.com",
  "version": "0.7.0",
  "suggestions": {

  },
  "platforms": {
    "openbsd": [

    ],
    "debian": [

    ],
    "fedora": [

    ],
    "centos": [

    ],
    "freebsd": [

    ],
    "ubuntu": [

    ],
    "redhat": [

    ]
  },
  "description": "Installs Capistrano gem and provides a define to set up deployment for an application",
  "conflicting": {

  },
  "providing": {
    "capistrano": [

    ]
  },
  "long_description": "",
  "replacing": {

  },
  "dependencies": {

  },
  "name": "capistrano",
  "attributes": {

  },
  "license": "Apache 2.0",
  "maintainer": "Opscode, Inc.",
  "recommendations": {

  }
}